{
  "earning": [
    {
      "orderNumber": "ord-00004",
      "orderDate": 1632298871000,
      "orderAmount": 10.5,
      "orderItem": 3
    },
    {
      "orderNumber": "ord-00003",
      "orderDate": 1632298871000,
      "orderAmount": 10.5,
      "orderItem": 2
    },
    {
      "orderNumber": "ord-00002",
      "orderDate": 1632298871000,
      "orderAmount": 10.5,
      "orderItem": 5
    },
    {
      "orderNumber": "ord-00001",
      "orderDate": 1632298871000,
      "orderAmount": 10.5,
      "orderItem": 1
    }
  ],
  "working-hours": [
    {
      "day": "Monday",
      "isActive": true,
      "slotOneStart": 1632355253000,
      "slotOneEnd": 1632330053000,
      "slotTwoStart": 1632376853000,
      "slotTwoEnd": 1632391253000
    },
    {
      "day": "Tuesday",
      "isActive": true,
      "slotOneStart": 1632355253000,
      "slotOneEnd": 1632330053000,
      "slotTwoStart": 1632376853000,
      "slotTwoEnd": 1632391253000
    },
    {
      "day": "Wednesday",
      "isActive": true,
      "slotOneStart": 1632355253000,
      "slotOneEnd": 1632330053000,
      "slotTwoStart": 1632376853000,
      "slotTwoEnd": 1632391253000
    },
    {
      "day": "Thursday",
      "isActive": true,
      "slotOneStart": 1632355253000,
      "slotOneEnd": 1632330053000,
      "slotTwoStart": 1632376853000,
      "slotTwoEnd": 1632391253000
    },
    {
      "day": "Friday",
      "isActive": true,
      "slotOneStart": 1632355253000,
      "slotOneEnd": 1632330053000,
      "slotTwoStart": 1632376853000,
      "slotTwoEnd": 1632391253000
    },
    {
      "day": "Saturday",
      "isActive": true,
      "slotOneStart": 1632355253000,
      "slotOneEnd": 1632330053000
    },
    {
      "day": "Sunday",
      "isActive": false,
      "slotOneStart": 1632298871000,
      "slotOneEnd": 1632330053000
    }
  ],
  "top-up-history-detail": [
    {
      "customerName": "Chan Thaily",
      "phoneNumber": "08909889080",
      "money": "100000៛",
      "time": 1632298871000,
      "staffName": "Mony"
    },
    {
      "customerName": "Chan Thaily",
      "phoneNumber": "08909889080",
      "money": "100000៛",
      "time": 1632298871000,
      "staffName": "Mony"
    },
    {
      "customerName": "Chan Thaily",
      "phoneNumber": "08909889080",
      "money": "100000៛",
      "time": 1632298871000,
      "staffName": "Mony"
    }
  ],
  "top-up-history": [
    {
      "dateTime": 1632298871000,
      "historyDetail": [
        {
          "customerName": "Chan Thaily",
          "phoneNumber": "08909889080",
          "money": "100000៛",
          "time": 1632298871000,
          "staffName": "Mony"
        },
        {
          "customerName": "Chan Thaily",
          "phoneNumber": "08909889080",
          "money": "100000៛",
          "time": 1632298871000,
          "staffName": "Mony"
        }
      ]
    },
    {
      "dateTime": 1632298871000,
      "historyDetail": [
        {
          "customerName": "Chan Thaily",
          "phoneNumber": "08909889080",
          "money": "100000៛",
          "time": 1632298871000,
          "staffName": "Mony"
        },
        {
          "customerName": "Chan Thaily",
          "phoneNumber": "08909889080",
          "money": "100000៛",
          "time": 1632298871000,
          "staffName": "Mony"
        }
      ]
    }
  ],
  "top-up-amount-suggestion": [
    {
      "id": 1,
      "amount": 10000
    },
    {
      "id": 2,
      "amount": 20000
    },
    {
      "id": 3,
      "amount": 40000
    },
    {
      "id": 4,
      "amount": 50000
    },
    {
      "id": 5,
      "amount": 100000
    },
    {
      "id": 6,
      "amount": 200000
    }
  ],
  "order": [
    {
      "id": 1,
      "orderNumber": "ord-00001",
      "orderDate": "23-09-2021 01:23",
      "orderAmount": 10.5,
      "orderItem": 3,
      "status": 0,
      "customerAddress": "No.395E0, St. Kampuchea Krom Corner \n221, Phsar Depo 3, Phnom Penh, \nCambodia.",
      "phone": "0982",
      "fee": 0,
      "orderdetailList": [
        {
          "title": "បាយមាន់ហៃណាំ",
          "quantity": 2,
          "currentPrice": 4.5,
          "normalPrice": 5.0,
          "totalamount": 9.0,
          "addItem": "Spicy, and more potato"
        },
        {
          "title": "បាយមាន់ហៃណាំ",
          "quantity": 2,
          "currentPrice": 4.5,
          "normalPrice": 5.0,
          "totalamount": 9.0,
          "addItem": "Spicy, and more potato"
        },
        {
          "title": "បាយមាន់ហៃណាំ",
          "quantity": 2,
          "currentPrice": 4.5,
          "normalPrice": 5.0,
          "totalamount": 9.0,
          "addItem": "Spicy, and more potato"
        }
      ]
    },
    {
      "id": 2,
      "orderNumber": "ord-00001",
      "orderDate": "23-09-2021 01:23",
      "orderAmount": 10.5,
      "orderItem": 3,
      "status": 0,
      "customerAddress": "No.395E0, St. Kampuchea Krom Corner \n221, Phsar Depo 3, Phnom Penh, \nCambodia.",
      "phone": "0982",
      "fee": 0,
      "orderdetailList": [
        {
          "title": "បាយមាន់ហៃណាំ",
          "quantity": 2,
          "currentPrice": 4.5,
          "normalPrice": 5.0,
          "totalamount": 9.0,
          "addItem": "Spicy, and more potato"
        },
        {
          "title": "បាយមាន់ហៃណាំ",
          "quantity": 2,
          "currentPrice": 4.5,
          "normalPrice": 5.0,
          "totalamount": 9.0,
          "addItem": "Spicy, and more potato"
        },
        {
          "title": "បាយមាន់ហៃណាំ",
          "quantity": 2,
          "currentPrice": 4.5,
          "normalPrice": 5.0,
          "totalamount": 9.0,
          "addItem": "Spicy, and more potato"
        }
      ]
    },
    {
      "id": 3,
      "orderNumber": "ord-00001",
      "orderDate": "23-09-2021 01:23",
      "orderAmount": 10.5,
      "orderItem": 3,
      "status": 1,
      "customerAddress": "No.395E0, St. Kampuchea Krom Corner \n221, Phsar Depo 3, Phnom Penh, \nCambodia.",
      "phone": "0982",
      "fee": 0,
      "orderdetailList": [
        {
          "title": "បាយមាន់ហៃណាំ",
          "quantity": 2,
          "currentPrice": 4.5,
          "normalPrice": 5.0,
          "totalamount": 9.0,
          "addItem": "Spicy, and more potato"
        },
        {
          "title": "បាយមាន់ហៃណាំ",
          "quantity": 2,
          "currentPrice": 4.5,
          "normalPrice": 5.0,
          "totalamount": 9.0,
          "addItem": "Spicy, and more potato"
        },
        {
          "title": "បាយមាន់ហៃណាំ",
          "quantity": 2,
          "currentPrice": 4.5,
          "normalPrice": 5.0,
          "totalamount": 9.0,
          "addItem": "Spicy, and more potato"
        }
      ]
    },
    {
      "id": 4,
      "orderNumber": "ord-00001",
      "orderDate": "23-09-2021 01:23",
      "orderAmount": 10.5,
      "orderItem": 3,
      "status": 2,
      "customerAddress": "No.395E0, St. Kampuchea Krom Corner \n221, Phsar Depo 3, Phnom Penh, \nCambodia.",
      "phone": "0982",
      "fee": 0,
      "orderdetailList": [
        {
          "title": "បាយមាន់ហៃណាំ",
          "quantity": 2,
          "currentPrice": 4.5,
          "normalPrice": 5.0,
          "totalamount": 9.0,
          "addItem": "Spicy, and more potato"
        },
        {
          "title": "បាយមាន់ហៃណាំ",
          "quantity": 2,
          "currentPrice": 4.5,
          "normalPrice": 5.0,
          "totalamount": 9.0,
          "addItem": "Spicy, and more potato"
        },
        {
          "title": "បាយមាន់ហៃណាំ",
          "quantity": 2,
          "currentPrice": 4.5,
          "normalPrice": 5.0,
          "totalamount": 9.0,
          "addItem": "Spicy, and more potato"
        }
      ]
    },
    {
      "id": 5,
      "orderNumber": "ord-00001",
      "orderDate": "23-09-2021 01:23",
      "orderAmount": 10.5,
      "orderItem": 3,
      "status": 3,
      "customerAddress": "No.395E0, St. Kampuchea Krom Corner \n221, Phsar Depo 3, Phnom Penh, \nCambodia.",
      "phone": "0982",
      "fee": 0,
      "orderdetailList": [
        {
          "title": "បាយមាន់ហៃណាំ",
          "quantity": 2,
          "currentPrice": 4.5,
          "normalPrice": 5.0,
          "totalamount": 9.0,
          "addItem": "Spicy, and more potato"
        },
        {
          "title": "បាយមាន់ហៃណាំ",
          "quantity": 2,
          "currentPrice": 4.5,
          "normalPrice": 5.0,
          "totalamount": 9.0,
          "addItem": "Spicy, and more potato"
        },
        {
          "title": "បាយមាន់ហៃណាំ",
          "quantity": 2,
          "currentPrice": 4.5,
          "normalPrice": 5.0,
          "totalamount": 9.0,
          "addItem": "Spicy, and more potato"
        }
      ]
    }
  ],
  "card-info": [
    {
      "id": 1,
      "customerId": 1,
      "customerName": "djjI",
      "cardNumber": "234567",
      "serial": "12345AH",
      "balance": 12.0,
      "point": 55
    },
    {
      "id": 2,
      "customerId": 2,
      "customerName": "djjI",
      "cardNumber": "234567",
      "serial": "12345AH",
      "balance": 12.0,
      "point": 55
    }
  ],
  "card-top-up-history": [
    {
      "id": 1,
      "cardId": 1,
      "dateTime": "10-07-2021 10:40 AM",
      "amount": 75.5
    },
    {
      "id": 2,
      "cardId": 1,
      "dateTime": "10-07-2021 10:40 AM",
      "amount": 75.5
    },
    {
      "id": 3,
      "cardId": 1,
      "dateTime": "10-07-2021 10:40 AM",
      "amount": 75.5
    },
    {
      "id": 4,
      "cardId": 1,
      "dateTime": "10-07-2021 10:40 AM",
      "amount": 75.5
    },
    {
      "id": 5,
      "cardId": 3,
      "dateTime": "10-07-2021 10:40 AM",
      "amount": 75.5
    },
    {
      "id": 6,
      "cardId": 2,
      "dateTime": "10-07-2021 10:40 AM",
      "amount": 75.5
    }
  ],
  "point-history": [
    {
      "id": 1,
      "cardId": 1,
      "dateTime": "10-07-2021 10:40 AM",
      "amount": 75.5,
      "point": 5
    },
    {
      "id": 2,
      "cardId": 1,
      "dateTime": "10-07-2021 10:40 AM",
      "amount": 75.5,
      "point": 5
    },
    {
      "id": 3,
      "cardId": 1,
      "dateTime": "10-07-2021 10:40 AM",
      "amount": 75.5,
      "point": 5
    },
    {
      "id": 4,
      "cardId": 1,
      "dateTime": "10-07-2021 10:40 AM",
      "amount": 75.5,
      "point": 5
    },
    {
      "id": 5,
      "cardId": 2,
      "dateTime": "10-07-2021 10:40 AM",
      "amount": 75.5,
      "point": 5
    }
  ],
  "notification": [
    {
      "id": 1,
      "imageUrl": "",
      "url": "",
      "title": "Happy for weekend days with turtle soup from Hengmart",
      "text": "It's the best for family party for lunch and evening",
      "dateTime": "2021-09-28 09:58:55 AM",
      "buttonTitle": "view",
      "isNew": true
    },
    {
      "id": 2,
      "imageUrl": "",
      "url": "",
      "title": "Special Price",
      "text": "New fruit just arrived gain benefit for your health",
      "dateTime": "2021-09-28 09:58:55 AM",
      "buttonTitle": "view",
      "isNew": true
    },
    {
      "id": 5,
      "imageUrl": "",
      "url": "",
      "title": "Red dragon fruit",
      "text": "Natural with sugary fresh and good for heath",
      "dateTime": "2021-09-28 09:58:55 AM",
      "buttonTitle": "Order Now",
      "isNew": false
    },
    {
      "id": 6,
      "imageUrl": "",
      "url": "",
      "title": "Red dragon fruit",
      "text": "Natural with sugary fresh and good for heath",
      "dateTime": "2021-09-28 09:58:55 AM",
      "buttonTitle": "Order Now",
      "isNew": false
    }
  ],
  "category": [
    {
      "id": 1,
      "name": "food",
      "parentId": 0,
      "thumnils": "https://www.pnglib.com/wp-content/uploads/2020/01/food_5e19ce7632e46.png"
    },
    {
      "id": 2,
      "name": "snack",
      "parentId": 0,
      "thumnils": "https://www.pngkey.com/png/full/4-49191_food-png-transparent-free-images-fast-food-clipart.png"
    },
    {
      "id": 3,
      "name": "fruit",
      "parentId": 0,
      "thumnils": "https://www.pngarts.com/files/11/Mix-Fruit-PNG-Image.png"
    },
    {
      "id": 4,
      "name": "drink",
      "parentId": 0,
      "thumnils": "https://www.freepnglogos.com/uploads/drinks-png/drinks-and-cocktails-14.png"
    },
    {
      "id": 5,
      "name": "sauce",
      "parentId": 0,
      "thumnils": "https://pngimg.com/uploads/sauce/sauce_PNG121.png"
    }
  ],
  "sub-category": [
    {
      "id": 6,
      "parentId": 1,
      "name": "Rice",
      "thumnils": "https://www.pngitem.com/pimgs/m/428-4284019_stir-fry-rice-and-vegetables-spiced-rice-hd.png"
    },
    {
      "id": 7,
      "parentId": 1,
      "name": "Soup",
      "thumnils": "https://www.pngitem.com/pimgs/m/428-4284019_stir-fry-rice-and-vegetables-spiced-rice-hd.png"
    },
    {
      "id": 8,
      "parentId": 1,
      "name": "Fried Rice",
      "thumnils": "https://www.pngitem.com/pimgs/m/428-4284019_stir-fry-rice-and-vegetables-spiced-rice-hd.png"
    },
    {
      "id": 9,
      "parentId": 1,
      "name": "Fried Food",
      "thumnils": "https://www.pngitem.com/pimgs/m/428-4284019_stir-fry-rice-and-vegetables-spiced-rice-hd.png"
    },
    {
      "id": 10,
      "parentId": 1,
      "name": "Sub cat",
      "thumnils": "https://www.pngitem.com/pimgs/m/428-4284019_stir-fry-rice-and-vegetables-spiced-rice-hd.png"
    },
    {
      "id": 11,
      "parentId": 2,
      "name": "Pops",
      "thumnils": "https://www.pngitem.com/pimgs/m/428-4284019_stir-fry-rice-and-vegetables-spiced-rice-hd.png"
    },
    {
      "id": 12,
      "parentId": 2,
      "name": "Chipsticks",
      "thumnils": "https://www.pngitem.com/pimgs/m/428-4284019_stir-fry-rice-and-vegetables-spiced-rice-hd.png"
    },
    {
      "id": 13,
      "parentId": 2,
      "name": "Chickatees",
      "thumnils": "https://www.pngitem.com/pimgs/m/428-4284019_stir-fry-rice-and-vegetables-spiced-rice-hd.png"
    },
    {
      "id": 14,
      "parentId": 2,
      "name": "Bacon Fries",
      "thumnils": "https://www.pngitem.com/pimgs/m/428-4284019_stir-fry-rice-and-vegetables-spiced-rice-hd.png"
    },
    {
      "id": 15,
      "parentId": 2,
      "name": "Jelly Beans",
      "thumnils": "https://www.pngitem.com/pimgs/m/428-4284019_stir-fry-rice-and-vegetables-spiced-rice-hd.png"
    },
    {
      "id": 16,
      "parentId": 3,
      "name": "Apple",
      "thumnils": "https://www.pngitem.com/pimgs/m/428-4284019_stir-fry-rice-and-vegetables-spiced-rice-hd.png"
    },
    {
      "id": 17,
      "parentId": 3,
      "name": "Grape",
      "thumnils": "https://www.pngitem.com/pimgs/m/428-4284019_stir-fry-rice-and-vegetables-spiced-rice-hd.png"
    },
    {
      "id": 18,
      "parentId": 3,
      "name": "Banana",
      "thumnils": "https://www.pngitem.com/pimgs/m/428-4284019_stir-fry-rice-and-vegetables-spiced-rice-hd.png"
    },
    {
      "id": 19,
      "parentId": 4,
      "name": "Mixed Drink",
      "thumnils": "https://www.pngitem.com/pimgs/m/428-4284019_stir-fry-rice-and-vegetables-spiced-rice-hd.png"
    },
    {
      "id": 20,
      "parentId": 4,
      "name": "Cocktail",
      "thumnils": "https://www.pngitem.com/pimgs/m/428-4284019_stir-fry-rice-and-vegetables-spiced-rice-hd.png"
    },
    {
      "id": 21,
      "parentId": 4,
      "name": "Juice",
      "thumnils": "https://www.pngitem.com/pimgs/m/428-4284019_stir-fry-rice-and-vegetables-spiced-rice-hd.png"
    },
    {
      "id": 22,
      "parentId": 5,
      "name": "Brown Sauce",
      "thumnils": "https://www.pngitem.com/pimgs/m/428-4284019_stir-fry-rice-and-vegetables-spiced-rice-hd.png"
    },
    {
      "id": 23,
      "parentId": 5,
      "name": "Butter Sauce",
      "thumnils": "https://www.pngitem.com/pimgs/m/428-4284019_stir-fry-rice-and-vegetables-spiced-rice-hd.png"
    },
    {
      "id": 24,
      "parentId": 5,
      "name": "Fish Sauce",
      "thumnils": "https://www.pngitem.com/pimgs/m/428-4284019_stir-fry-rice-and-vegetables-spiced-rice-hd.png"
    },
    {
      "id": 25,
      "parentId": 5,
      "name": "Tomato Sauce",
      "thumnils": "https://www.pngitem.com/pimgs/m/428-4284019_stir-fry-rice-and-vegetables-spiced-rice-hd.png"
    }
  ],
  "product": [
    {
      "id": 1,
      "categoryId": 1,
      "subCategoryId": 6,
      "name": "បាយមាន់ហៃណាំ",
      "price": 10000,
      "imageUrl": "https://raw.githubusercontent.com/hengmart/hengmart-api/main/images/foodc.png",
      "isActive": true,
      "isFavorite": true
    },
    {
      "id": 2,
      "categoryId": 1,
      "subCategoryId": 10,
      "name": "ភ្លាសាច់គោ",
      "price": 12000,
      "imageUrl": "https://raw.githubusercontent.com/hengmart/hengmart-api/main/images/a17.jpeg",
      "isActive": true,
      "isFavorite": true
    },
    {
      "id": 3,
      "categoryId": 1,
      "subCategoryId": 9,
      "name": "ឆាក្ដាមម្រេចខ្ចី",
      "price": 18000,
      "imageUrl": "https://raw.githubusercontent.com/hengmart/hengmart-api/main/images/a19.jpeg",
      "isActive": true,
      "isFavorite": true
    },
    {
      "id": 4,
      "categoryId": 2,
      "subCategoryId": 11,
      "name": "berger",
      "price": 12000,
      "imageUrl": "https://raw.githubusercontent.com/hengmart/hengmart-api/main/images/b.png",
      "isActive": false,
      "isFavorite": true
    },
    {
      "id": 5,
      "categoryId": 2,
      "subCategoryId": 12,
      "name": "sandwich",
      "price": 10000,
      "imageUrl": "https://raw.githubusercontent.com/hengmart/hengmart-api/main/images/s.jpg",
      "isActive": true,
      "isFavorite": false
    },
    {
      "id": 6,
      "categoryId": 3,
      "subCategoryId": 18,
      "name": "ចេក",
      "price": 6000,
      "imageUrl": "https://raw.githubusercontent.com/hengmart/hengmart-api/main/images/f3.jpg",
      "isActive": false,
      "isFavorite": false
    },
    {
      "id": 7,
      "categoryId": 3,
      "subCategoryId": 17,
      "name": "ទំពាំងបាយជូរ",
      "price": 20000,
      "imageUrl": "https://raw.githubusercontent.com/hengmart/hengmart-api/main/images/f1.jpg",
      "isActive": true,
      "isFavorite": false
    },
    {
      "id": 8,
      "categoryId": 3,
      "subCategoryId": 17,
      "name": "ក្រូច",
      "price": 8000,
      "imageUrl": "https://raw.githubusercontent.com/hengmart/hengmart-api/main/images/f2.jpg",
      "isActive": true,
      "isFavorite": false
    },
    {
      "id": 9,
      "categoryId": 4,
      "subCategoryId": 21,
      "name": "Pepsi",
      "price": 20000,
      "imageUrl": "https://raw.githubusercontent.com/hengmart/hengmart-api/main/images/f1.jpg",
      "isActive": true,
      "isFavorite": false
    },
    {
      "id": 10,
      "categoryId": 4,
      "subCategoryId": 20,
      "name": "Coke",
      "price": 8000,
      "imageUrl": "https://raw.githubusercontent.com/hengmart/hengmart-api/main/images/f2.jpg",
      "isActive": true,
      "isFavorite": false
    },
    {
      "id": 11,
      "categoryId": 5,
      "subCategoryId": 23,
      "name": "Suki Sauce",
      "price": 20000,
      "imageUrl": "https://raw.githubusercontent.com/hengmart/hengmart-api/main/images/f1.jpg",
      "isActive": true,
      "isFavorite": true
    },
    {
      "id": 12,
      "categoryId": 5,
      "subCategoryId": 22,
      "name": "Salad Cream",
      "price": 8000,
      "imageUrl": "https://raw.githubusercontent.com/hengmart/hengmart-api/main/images/f2.jpg",
      "isActive": true,
      "isFavorite": false
    }
  ],
  "special-offer": [
    {
      "id": 1,
      "name": "បាយមាន់ហៃណាំ",
      "normalPrice": 5.5,
      "currentPrice": 3.25,
      "discount": 2.25,
      "isFavorite": true,
      "categoryId": 3,
      "rating": 1.5,
      "imageUrl": "https://raw.githubusercontent.com/hengmart/hengmart-api/main/images/foodc.png"
    },
    {
      "id": 2,
      "name": "ភ្លាសាច់គោ",
      "normalPrice": 5.5,
      "currentPrice": 3.25,
      "discount": 2.25,
      "isFavorite": true,
      "categoryId": 2,
      "rating": 1.5,
      "imageUrl": "https://raw.githubusercontent.com/hengmart/hengmart-api/main/images/a17.jpeg"
    },
    {
      "id": 3,
      "name": "ឆាក្ដាមម្រេចខ្ចី",
      "normalPrice": 5.5,
      "currentPrice": 3.25,
      "discount": 2.25,
      "isFavorite": true,
      "categoryId": 2,
      "rating": 1.5,
      "imageUrl": "https://raw.githubusercontent.com/hengmart/hengmart-api/main/images/a19.jpeg"
    }
  ],
  "lunch-box": [
    {
      "id": 3,
      "name": "ឆាក្ដាមម្រេចខ្ចី",
      "normalPrice": 5.5,
      "currentPrice": 3.25,
      "discount": 2.25,
      "isFavorite": true,
      "categoryId": 3,
      "rating": 1.5,
      "imageUrl": "https://raw.githubusercontent.com/hengmart/hengmart-api/main/images/a19.jpeg"
    },
    {
      "id": 4,
      "name": "berger",
      "normalPrice": 5.5,
      "currentPrice": 3.25,
      "discount": 2.25,
      "isFavorite": true,
      "categoryId": 5,
      "rating": 1.5,
      "imageUrl": "https://raw.githubusercontent.com/hengmart/hengmart-api/main/images/b.png"
    },
    {
      "id": 5,
      "name": "sandwich",
      "normalPrice": 5.5,
      "currentPrice": 3.25,
      "discount": 2.25,
      "isFavorite": true,
      "categoryId": 1,
      "rating": 1.5,
      "imageUrl": "https://raw.githubusercontent.com/hengmart/hengmart-api/main/images/s.jpg"
    }
  ],
  "popular": [
    {
      "id": 5,
      "name": "sandwich",
      "normalPrice": 5.5,
      "currentPrice": 3.25,
      "discount": 2.25,
      "isFavorite": true,
      "categoryId": 1,
      "rating": 1.5,
      "imageUrl": "https://raw.githubusercontent.com/hengmart/hengmart-api/main/images/s.jpg"
    },
    {
      "id": 6,
      "name": "ចេក",
      "normalPrice": 5.5,
      "currentPrice": 3.25,
      "discount": 2.25,
      "isFavorite": true,
      "categoryId": 2,
      "rating": 1.5,
      "imageUrl": "https://raw.githubusercontent.com/hengmart/hengmart-api/main/images/f3.jpg"
    },
    {
      "id": 7,
      "name": "ទំពាំងបាយជូរ",
      "normalPrice": 5.5,
      "currentPrice": 3.25,
      "discount": 2.25,
      "isFavorite": true,
      "categoryId": 3,
      "rating": 1.5,
      "imageUrl": "https://raw.githubusercontent.com/hengmart/hengmart-api/main/images/f1.jpg"
    },
    {
      "id": 8,
      "name": "ក្រូច",
      "normalPrice": 5.5,
      "currentPrice": 3.25,
      "discount": 2.25,
      "isFavorite": true,
      "categoryId": 1,
      "rating": 1.5,
      "imageUrl": "https://raw.githubusercontent.com/hengmart/hengmart-api/main/images/f2.jpg"
    }
  ],
  "party-set": [
    {
      "id": 1,
      "setName": "ទំពាំងបាយជូរ",
      "people": 5,
      "normalPrice": 5.5,
      "currentPrice": 3.25,
      "discount": 2.25,
      "isFavorite": true,
      "categoryId": 1,
      "rating": 1.5,
      "imageUrl": "https://raw.githubusercontent.com/hengmart/hengmart-api/main/images/f1.jpg"
    },
    {
      "id": 2,
      "setName": "ក្រូច",
      "people": 9,
      "normalPrice": 5.5,
      "currentPrice": 3.25,
      "discount": 2.25,
      "isFavorite": true,
      "categoryId": 4,
      "rating": 1.5,
      "imageUrl": "https://raw.githubusercontent.com/hengmart/hengmart-api/main/images/f2.jpg"
    }
  ],
  "test": [
    {
      "id": 30
    },
    {
      "id": 20
    }
  ],
  "category_list": [
    {
      "id": 1,
      "categoryName": "food",
      "categoryId": 1,
      "listDetail": [
        {
          "name": "abc",
          "price": 0,
          "isActive": 0,
          "imageUrl": ""
        },
        {
          "name": "dd",
          "price": 0,
          "isActive": 0,
          "imageUrl": ""
        },
        {
          "name": "ijis",
          "price": 0,
          "isActive": 0,
          "imageUrl": ""
        },
        {
          "name": "jisj",
          "price": 0,
          "isActive": 0,
          "imageUrl": ""
        },
        {
          "name": "jijs",
          "price": 0,
          "isActive": 0,
          "imageUrl": ""
        }
      ]
    },
    {
      "id": 2,
      "categoryName": "snack",
      "categoryId": 2,
      "listDetail": [
        {
          "name": "skjs",
          "price": 0,
          "isActive": 0,
          "imageUrl": ""
        },
        {
          "name": "kjs",
          "price": 0,
          "isActive": 0,
          "imageUrl": ""
        },
        {
          "name": "skjos",
          "price": 0,
          "isActive": 0,
          "imageUrl": ""
        },
        {
          "name": "mksls",
          "price": 0,
          "isActive": 0,
          "imageUrl": ""
        }
      ]
    },
    {
      "id": 3,
      "categoryName": "fruit",
      "categoryId": 3,
      "listDetail": [
        {
          "name": "kjns",
          "price": 0,
          "isActive": 0,
          "imageUrl": ""
        },
        {
          "name": "kjskjs",
          "price": 0,
          "isActive": 0,
          "imageUrl": ""
        },
        {
          "name": "kjnjks",
          "price": 0,
          "isActive": 0,
          "imageUrl": ""
        }
      ]
    },
    {
      "id": 4,
      "categoryName": "drink",
      "categoryId": 4,
      "listDetail": [
        {
          "name": "sdkjs",
          "price": 0,
          "isActive": 0,
          "imageUrl": ""
        },
        {
          "name": "skijjso",
          "price": 0,
          "isActive": 0,
          "imageUrl": ""
        }
      ]
    },
    {
      "id": 5,
      "categoryName": "sauce",
      "categoryId": 5,
      "listDetail": [
        {
          "name": "skjs",
          "price": 0,
          "isActive": 0,
          "imageUrl": ""
        }
      ]
    }
  ],
  "address": [
    {
      "id": 1,
      "title": "work",
      "address": "Address : Floor 4th,No. 85-88, St. Kim il Sung (289), Sangkat Boeng Kak II, Khan Tuol Kouk, Phnom Penh, Kingdom of Cambodia., Samdach Penn Nouth St. (289), Phnom Penh",
      "isDefault": true,
      "latitude": 214124124,
      "longitude": 89068023
    },
    {
      "id": 2,
      "title": "home",
      "address": "Address :  St. Kim il Sung (289), Sangkat Boeng Kak II, Khan Tuol Kouk, Phnom Penh, Kingdom of Cambodia., Samdach Penn Nouth St. (289), Phnom Penh",
      "isDefault": false,
      "latitude": 256,
      "longitude": 856
    },
    {
      "id": 3,
      "title": "mart",
      "address": "Address : Floor 4th,No. 85-88,Sangkat Boeng Kak II, Khan Tuol Kouk, Phnom Penh, Kingdom of Cambodia., Samdach Penn Nouth St. (289), Phnom Penh",
      "isDefault": false,
      "latitude": 245,
      "longitude": 796
    },
    {
      "id": 4,
      "title": "office",
      "address": "Address : Floor 4th,No. 85-88, St. Kim il Sung (289)",
      "isDefault": false,
      "latitude": 23562356,
      "longitude": 9657478
    }
  ],
  "dealerInfo": [
    {
      "id": 1,
      "totalCustomer": 25,
      "benefitOfToday": 234,
      "benefitTodayDate": 1632298871000,
      "totalBenefit": 234,
      "totalBenefitStartDate": 1632298871000,
      "totalBenefitEndDate": 1632298871000,
      "couponCode": "doem"
    },
    {
      "id": 2,
      "totalCustomer": 15,
      "benefitOfToday": 2345,
      "benefitTodayDate": 1632298871000,
      "totalBenefit": 456,
      "totalBenefitStartDate": 1632298871000,
      "totalBenefitEndDate": 1632298871000,
      "couponCode": "mony"
    },
    {
      "id": 3,
      "totalCustomer": 45,
      "benefitOfToday": 678,
      "benefitTodayDate": 1632298871000,
      "totalBenefit": 275,
      "totalBenefitStartDate": 1632298871000,
      "totalBenefitEndDate": 1632298871000,
      "couponCode": "roth"
    }
  ],
  "dealerTransaction": [
    {
      "id": 1,
      "dateTime": 1632298871000,
      "customerName": "moru",
      "amount": 324,
      "benefit": 2
    },
    {
      "id": 2,
      "dateTime": 1632298871000,
      "customerName": "morw",
      "amount": 56,
      "benefit": 1
    },
    {
      "id": 3,
      "dateTime": 1632298871000,
      "customerName": "moro",
      "amount": 34,
      "benefit": 9
    }
  ],
  "dealerCustomer": [
    {
      "id": 1,
      "name": "mony",
      "phoneNumber": "0998303983",
      "orderAmount": 200,
      "registerDate": 1632298871000
    },
    {
      "id": 2,
      "name": "mroro",
      "phoneNumber": "0234892934",
      "orderAmount": 100,
      "registerDate": 1632298871000
    },
    {
      "id": 3,
      "name": "toyj",
      "phoneNumber": "0127823434",
      "orderAmount": 20,
      "registerDate": 1632298871000
    },
    {
      "id": 4,
      "name": "hong",
      "phoneNumber": "0892342342",
      "orderAmount": 10,
      "registerDate": 1632298871000
    }
  ],
  "cart": [
    {
      "id": 1,
      "subtotal": 18.5,
      "itemDiscount": 3.0,
      "couponDiscount": 0.5,
      "deliveryFee": 0.0,
      "items": [
        {
          "itemId": 1,
          "itemName": "something",
          "itemPrice": 5.5,
          "priceAfterDiscount": 4.5,
          "qty": 2,
          "itemType": "product",
          "imageUrl": "https://raw.githubusercontent.com/hengmart/hengmart-api/main/images/foodc.png"
        },
        {
          "itemId": 1,
          "itemName": "nothing",
          "itemPrice": 5.5,
          "priceAfterDiscount": 4.5,
          "qty": 1,
          "itemType": "product",
          "imageUrl": "https://raw.githubusercontent.com/hengmart/hengmart-api/main/images/foodc.png"
        },
        {
          "itemId": 1,
          "naitemNameme": "product name",
          "itemPrice": 5.5,
          "priceAfterDiscount": 4.5,
          "qty": 3,
          "itemType": "product",
          "imageUrl": "https://raw.githubusercontent.com/hengmart/hengmart-api/main/images/foodc.png"
        }
      ]
    }
  ]
}
